[
    {
        "No.": 1,
        "Kecamatan": "Kec. Lima Puluh",
        "Kota": "Kota Pekanbaru",
        "Provinsi": "Riau",
        "Kode Pos": 28155,
        "Negara": "Indonesia",
        "Latitude": 0.538095,
        "Longititude": 101.454058,
        "Nama Toko": "Indomaret"
    },
    {
        "No.": 2,
        "Kecamatan": "Kec. Lima Puluh",
        "Kota": "Kota Pekanbaru",
        "Provinsi": "Riau",
        "Kode Pos": 28143,
        "Negara": "Indonesia",
        "Latitude": 0.539027,
        "Longititude": 101.45865,
        "Nama Toko": "Indomaret"
    },
    {
        "No.": 3,
        "Kecamatan": "Kec. Lima Puluh",
        "Kota": "Kota Pekanbaru",
        "Provinsi": "Riau",
        "Kode Pos": 28151,
        "Negara": "Indonesia",
        "Latitude": 0.53189,
        "Longititude": 101.459191,
        "Nama Toko": "Indomaret"
    },
    {
        "No.": 4,
        "Kecamatan": "Kec. Lima Puluh",
        "Kota": "Kota Pekanbaru",
        "Provinsi": "Riau",
        "Kode Pos": 28151,
        "Negara": "Indonesia",
        "Latitude": 0.531702,
        "Longititude": 101.465364,
        "Nama Toko": "Indomaret Fresh"
    },
    {
        "No.": 5,
        "Kecamatan": "Kec. Tenayan Raya",
        "Kota": "Kota Pekanbaru",
        "Provinsi": "Riau",
        "Kode Pos": 28112,
        "Negara": "Indonesia",
        "Latitude": 0.530335,
        "Longititude": 101.48036,
        "Nama Toko": "Indomaret"
    },
    {
        "No.": 6,
        "Kecamatan": "Kec. Lima Puluh",
        "Kota": "Kota Pekanbaru",
        "Provinsi": "Riau",
        "Kode Pos": 28156,
        "Negara": "Indonesia",
        "Latitude": 0.528271,
        "Longititude": 101.456788,
        "Nama Toko": "Alfarmart"
    },
    {
        "No.": 7,
        "Kecamatan": "Kec. Tenayan Raya",
        "Kota": "Kota Pekanbaru",
        "Provinsi": "Riau",
        "Kode Pos": 28281,
        "Negara": "Indonesia",
        "Latitude": 0.532331,
        "Longititude": 101.47279,
        "Nama Toko": "Alfarmart"
    },
    {
        "No.": 8,
        "Kecamatan": "Kec. Lima Puluh",
        "Kota": "Kota Pekanbaru",
        "Provinsi": "Riau",
        "Kode Pos": 28155,
        "Negara": "Indonesia",
        "Latitude": 0.529465,
        "Longititude": 101.456524,
        "Nama Toko": "Indomaret"
    },
    {
        "No.": 9,
        "Kecamatan": "Kec. Tenayan Raya",
        "Kota": "Kota Pekanbaru",
        "Provinsi": "Riau",
        "Kode Pos": 28151,
        "Negara": "Indonesia",
        "Latitude": 0.532926,
        "Longititude": 101.468951,
        "Nama Toko": "Indomaret"
    },
    {
        "No.": 10,
        "Kecamatan": "Rumbai",
        "Kota": "Kota Pekanbaru",
        "Provinsi": "Riau",
        "Kode Pos": 28262,
        "Negara": "Indonesia",
        "Latitude": 0.569061,
        "Longititude": 101.426325,
        "Nama Toko": "Alfarmart",
        "Gambar":"https://drive.google.com/uc?export=view&id=1kslSK7HG8rEd03AktUYAu73ww9bT2mZ6"
    },
    {
        "No.": 11,
        "Kecamatan": "Rumbai",
        "Kota": "Pekanbaru",
        "Provinsi": "Riau",
        "Kode Pos": 28262,
        "Negara": "Indonesia",
        "Latitude": 0.568706,
        "Longititude": 101.419288,
        "Nama Toko": "Alfarmart"
    },
    {
        "No.": 12,
        "Kecamatan": "Tenayan Raya",
        "Kota": "Pekanbaru",
        "Provinsi": "Riau",
        "Kode Pos": 28112,
        "Negara": "Indonesia",
        "Latitude": 0.524244,
        "Longititude": 101.475461,
        "Nama Toko": "Indomaret"
    },
    {
        "No.": 13,
        "Kecamatan": "Rumbai",
        "Kota": "Pekanbaru",
        "Provinsi": "Riau",
        "Kode Pos": 28262,
        "Negara": "Indonesia",
        "Latitude": 0.569002,
        "Longititude": 101.427739,
        "Nama Toko": "Indomaret"
    },
    {
        "No.": 14,
        "Kecamatan": "Sail",
        "Kota": "Pekanbaru",
        "Provinsi": "Riau",
        "Kode Pos": 28133,
        "Negara": "Indonesia",
        "Latitude": 0.524905,
        "Longititude": 101.462352,
        "Nama Toko": "Indomaret"
    },
    {
        "No.": 15,
        "Kecamatan": "Rumbai",
        "Kota": "Pekanbaru",
        "Provinsi": "Riau",
        "Kode Pos": 28262,
        "Negara": "Indonesia",
        "Latitude": 0.568559,
        "Longititude": 101.418929,
        "Nama Toko": "Indomaret"
    },
    {
        "No.": 16,
        "Kecamatan": "Tenayan Raya",
        "Kota": "Pekanbaru",
        "Provinsi": "Riau",
        "Kode Pos": 28112,
        "Negara": "Indonesia",
        "Latitude": 0.524978,
        "Longititude": 101.479293,
        "Nama Toko": "Alfarmart"
    },
    {
        "No.": 17,
        "Kecamatan": "Tenayan Raya",
        "Kota": "Pekanbaru",
        "Provinsi": "Riau",
        "Kode Pos": 28111,
        "Negara": "Indonesia",
        "Latitude": 0.52472,
        "Longititude": 101.468112,
        "Nama Toko": "Indomaret"
    },
    {
        "No.": 18,
        "Kecamatan": "Rumbai",
        "Kota": "Pekanbaru",
        "Provinsi": "Riau",
        "Kode Pos": 28262,
        "Negara": "Indonesia",
        "Latitude": 0.569076,
        "Longititude": 101.425138,
        "Nama Toko": "Indomaret"
    },
    {
        "No.": 19,
        "Kecamatan": "Rumbai",
        "Kota": "Pekanbaru",
        "Provinsi": "Riau",
        "Kode Pos": 28262,
        "Negara": "Indonesia",
        "Latitude": 0.564306,
        "Longititude": 101.431615,
        "Nama Toko": "Indomaret"
    },
    {
        "No.": 20,
        "Kecamatan": "Rumbai",
        "Kota": "Pekanbaru",
        "Provinsi": "Riau",
        "Kode Pos": 28292,
        "Negara": "Indonesia",
        "Latitude": 0.56016,
        "Longititude": 101.438389,
        "Nama Toko": "Indomaret"
    },
    {
        "No.": 21,
        "Kecamatan": "Rumbai",
        "Kota": "Pekanbaru",
        "Provinsi": "Riau",
        "Kode Pos": 28262,
        "Negara": "Indonesia",
        "Latitude": 0.570785,
        "Longititude": 101.448482,
        "Nama Toko": "Indomaret"
    },
    {
        "No.": 22,
        "Kecamatan": "Bukit Raya",
        "Kota": "Pekanbaru",
        "Provinsi": "Riau",
        "Kode Pos": 28292,
        "Negara": "Indonesia",
        "Latitude": 0.49922,
        "Longititude": 101.464653,
        "Nama Toko": "Indomaret"
    },
    {
        "No.": 23,
        "Kecamatan": "Rumbai",
        "Kota": "Pekanbaru",
        "Provinsi": "Riau",
        "Kode Pos": 28262,
        "Negara": "Indonesia",
        "Latitude": 0.569327,
        "Longititude": 101.443456,
        "Nama Toko": "Indomaret Fresh"
    },
    {
        "No.": 24,
        "Kecamatan": "Rumbai",
        "Kota": "Pekanbaru",
        "Provinsi": "Riau",
        "Kode Pos": 28292,
        "Negara": "Indonesia",
        "Latitude": 0.560597,
        "Longititude": 101.445357,
        "Nama Toko": "Indomaret"
    },
    {
        "No.": 25,
        "Kecamatan": "Rumbai",
        "Kota": "Pekanbaru",
        "Provinsi": "Riau",
        "Kode Pos": 28292,
        "Negara": "Indonesia",
        "Latitude": 0.56074,
        "Longititude": 101.432514,
        "Nama Toko": "Alfarmart"
    },
    {
        "No.": 26,
        "Kecamatan": "Rumbai",
        "Kota": "Pekanbaru",
        "Provinsi": "Riau",
        "Kode Pos": 28262,
        "Negara": "Indonesia",
        "Latitude": 0.563801,
        "Longititude": 101.449167,
        "Nama Toko": "Indomaret"
    },
    {
        "No.": 27,
        "Kecamatan": "Rumbai",
        "Kota": "Pekanbaru",
        "Provinsi": "Riau",
        "Kode Pos": 28262,
        "Negara": "Indonesia",
        "Latitude": 0.559792,
        "Longititude": 101.436682,
        "Nama Toko": "Alfarmart"
    },
    {
        "No.": 28,
        "Kecamatan": "Rumbai",
        "Kota": "Pekanbaru",
        "Provinsi": "Riau",
        "Kode Pos": 28262,
        "Negara": "Indonesia",
        "Latitude": 0.570912,
        "Longititude": 101.453233,
        "Nama Toko": "Alfarmart"
    },
    {
        "No.": 29,
        "Kecamatan": "Rumbai",
        "Kota": "Pekanbaru",
        "Provinsi": "Riau",
        "Kode Pos": 28292,
        "Negara": "Indonesia",
        "Latitude": 0.560376,
        "Longititude": 101.446276,
        "Nama Toko": "Alfarmart"
    },
    {
        "No.": 30,
        "Kecamatan": "Marpoyan Damai",
        "Kota": "Pekanbaru",
        "Provinsi": "Riau",
        "Kode Pos": 28125,
        "Negara": "Indonesia",
        "Latitude": 0.507324,
        "Longititude": 101.450549,
        "Nama Toko": "Indomaret"
    },
    {
        "No.": 31,
        "Kecamatan": "Marpoyan Damai",
        "Kota": "Pekanbaru",
        "Provinsi": "Riau",
        "Kode Pos": 28292,
        "Negara": "Indonesia",
        "Latitude": 0.502226,
        "Longititude": 101.425215,
        "Nama Toko": "Indomaret Fresh"
    },
    {
        "No.": 32,
        "Kecamatan": "Lima Puluh",
        "Kota": "Pekanbaru",
        "Provinsi": "Riau",
        "Kode Pos": 28292,
        "Negara": "Indonesia",
        "Latitude": 0.531924,
        "Longititude": 101.459278,
        "Nama Toko": "Indomaret"
    },
    {
        "No.": 33,
        "Kecamatan": "Rumbai",
        "Kota": "Pekanbaru",
        "Provinsi": "Riau",
        "Kode Pos": 28292,
        "Negara": "Indonesia",
        "Latitude": 0.560597,
        "Longititude": 101.445357,
        "Nama Toko": "Indomaret"
    },
    {
        "No.": 34,
        "Kecamatan": "Rumbai",
        "Kota": "Pekanbaru",
        "Provinsi": "Riau",
        "Kode Pos": 28262,
        "Negara": "Indonesia",
        "Latitude": 0.563801,
        "Longititude": 101.449167,
        "Nama Toko": "Indomaret"
    },
    {
        "No.": 35,
        "Kecamatan": "Senapelan",
        "Kota": "Pekanbaru",
        "Provinsi": "Riau",
        "Kode Pos": 28292,
        "Negara": "Indonesia",
        "Latitude": 0.536015,
        "Longititude": 101.444605,
        "Nama Toko": "Indomaret"
    },
    {
        "No.": 36,
        "Kecamatan": "Senapelan",
        "Kota": "Pekanbaru",
        "Provinsi": "Riau",
        "Kode Pos": 28292,
        "Negara": "Indonesia",
        "Latitude": 0.535347,
        "Longititude": 101.430179,
        "Nama Toko": "Indomaret"
    },
    {
        "No.": 37,
        "Kecamatan": "Bukit Raya",
        "Kota": "Pekanbaru",
        "Provinsi": "Riau",
        "Kode Pos": 28292,
        "Negara": "Indonesia",
        "Latitude": 0.494231,
        "Longititude": 101.458237,
        "Nama Toko": "Indomaret"
    },
    {
        "No.": 38,
        "Kecamatan": "Rumbai",
        "Kota": "Pekanbaru",
        "Provinsi": "Riau",
        "Kode Pos": 28262,
        "Negara": "Indonesia",
        "Latitude": 0.570785,
        "Longititude": 101.448482,
        "Nama Toko": "Indomaret"
    },
    {
        "No.": 39,
        "Kecamatan": "Rumbai",
        "Kota": "Pekanbaru",
        "Provinsi": "Riau",
        "Kode Pos": 28262,
        "Negara": "Indonesia",
        "Latitude": 0.56645,
        "Longititude": 101.448428,
        "Nama Toko": "Alfarmart"
    },
    {
        "No.": 40,
        "Kecamatan": "Tenayan Raya",
        "Kota": "Pekanbaru",
        "Provinsi": "Riau",
        "Kode Pos": 28281,
        "Negara": "Indonesia",
        "Latitude": 0.50421,
        "Longititude": 101.5091,
        "Nama Toko": "Indomaret"
    },
    {
        "No.": 41,
        "Kecamatan": "Tenayan Raya",
        "Kota": "Pekanbaru",
        "Provinsi": "Riau",
        "Kode Pos": 28282,
        "Negara": "Indonesia",
        "Latitude": 0.4961,
        "Longititude": 101.501405,
        "Nama Toko": "Indomaret"
    },
    {
        "No.": 42,
        "Kecamatan": "Tenayan Raya",
        "Kota": "Pekanbaru",
        "Provinsi": "Riau",
        "Kode Pos": 28281,
        "Negara": "Indonesia",
        "Latitude": 0.519833,
        "Longititude": 101.482523,
        "Nama Toko": "Alfarmart"
    },
    {
        "No.": 43,
        "Kecamatan": "Tenayan Raya",
        "Kota": "Pekanbaru",
        "Provinsi": "Riau",
        "Kode Pos": 28112,
        "Negara": "Indonesia",
        "Latitude": 0.524967,
        "Longititude": 101.479267,
        "Nama Toko": "Alfarmart"
    },
    {
        "No.": 44,
        "Kecamatan": "Tenayan Raya",
        "Kota": "Pekanbaru",
        "Provinsi": "Riau",
        "Kode Pos": 28131,
        "Negara": "Indonesia",
        "Latitude": 0.513103,
        "Longititude": 101.489837,
        "Nama Toko": "Indomaret"
    },
    {
        "No.": 45,
        "Kecamatan": "Tenayan Raya",
        "Kota": "Pekanbaru",
        "Provinsi": "Riau",
        "Kode Pos": 28141,
        "Negara": "Indonesia",
        "Latitude": 0.519393,
        "Longititude": 101.482885,
        "Nama Toko": "Indomaret"
    },
    {
        "No.": 46,
        "Kecamatan": "Tenayan Raya",
        "Kota": "Pekanbaru",
        "Provinsi": "Riau",
        "Kode Pos": 28141,
        "Negara": "Indonesia",
        "Latitude": 0.53025,
        "Longititude": 101.48028,
        "Nama Toko": "Indomaret"
    },
    {
        "No.": 47,
        "Kecamatan": "Tenayan Raya",
        "Kota": "Pekanbaru",
        "Provinsi": "Riau",
        "Kode Pos": 28131,
        "Negara": "Indonesia",
        "Latitude": 0.507667,
        "Longititude": 101.496108,
        "Nama Toko": "Indomaret"
    },
    {
        "No.": 48,
        "Kecamatan": "Tenayan Raya",
        "Kota": "Pekanbaru",
        "Provinsi": "Riau",
        "Kode Pos": 28289,
        "Negara": "Indonesia",
        "Latitude": 0.496082,
        "Longititude": 101.501263,
        "Nama Toko": "Indomaret"
    },
    {
        "No.": 49,
        "Kecamatan": "Tenayan Raya",
        "Kota": "Pekanbaru",
        "Provinsi": "Riau",
        "Kode Pos": 28131,
        "Negara": "Indonesia",
        "Latitude": 0.495462,
        "Longititude": 101.491862,
        "Nama Toko": "Indomaret"
    },
    {
        "No.": 50,
        "Kecamatan": "Bukit Raya",
        "Kota": "Pekanbaru",
        "Provinsi": "Riau",
        "Kode Pos": 28281,
        "Negara": "Indonesia",
        "Latitude": 0.500517,
        "Longititude": 101.470738,
        "Nama Toko": "Indomaret"
    },
    {
        "No.": 51,
        "Kecamatan": "Bukit Raya",
        "Kota": "Pekanbaru",
        "Provinsi": "Riau",
        "Kode Pos": 28292,
        "Negara": "Indonesia",
        "Latitude": 0.53517,
        "Longititude": 101.429696,
        "Nama Toko": "Indomaret"
    },
    {
        "No.": 52,
        "Kecamatan": "Tenayan Raya",
        "Kota": "Pekanbaru",
        "Provinsi": "Riau",
        "Kode Pos": 28131,
        "Negara": "Indonesia",
        "Latitude": 0.494803,
        "Longititude": 101.483898,
        "Nama Toko": "Alfarmart"
    },
    {
        "No.": 53,
        "Kecamatan": "Bukit Raya",
        "Kota": "Pekanbaru",
        "Provinsi": "Riau",
        "Kode Pos": 28126,
        "Negara": "Indonesia",
        "Latitude": 0.500238,
        "Longititude": 101.476908,
        "Nama Toko": "Indomaret"
    },
    {
        "No.": 54,
        "Kecamatan": "Bukit Raya",
        "Kota": "Pekanbaru",
        "Provinsi": "Riau",
        "Kode Pos": 28282,
        "Negara": "Indonesia",
        "Latitude": 0.500168,
        "Longititude": 101.47702,
        "Nama Toko": "Indomaret"
    },
    {
        "No.": 55,
        "Kecamatan": "Bukit Raya",
        "Kota": "Pekanbaru",
        "Provinsi": "Riau",
        "Kode Pos": 28131,
        "Negara": "Indonesia",
        "Latitude": 0.50076,
        "Longititude": 101.475693,
        "Nama Toko": "Indomaret"
    },
    {
        "No.": 56,
        "Kecamatan": "Tenayan Raya",
        "Kota": "Pekanbaru",
        "Provinsi": "Riau",
        "Kode Pos": 28131,
        "Negara": "Indonesia",
        "Latitude": 0.49545,
        "Longititude": 101.491783,
        "Nama Toko": "Indomaret"
    },
    {
        "No.": 57,
        "Kecamatan": "Bukit Raya",
        "Kota": "Pekanbaru",
        "Provinsi": "Riau",
        "Kode Pos": 28131,
        "Negara": "Indonesia",
        "Latitude": 0.500198,
        "Longititude": 101.47698,
        "Nama Toko": "Indomaret"
    },
    {
        "No.": 58,
        "Kecamatan": "Tenayan Raya",
        "Kota": "Pekanbaru",
        "Provinsi": "Riau",
        "Kode Pos": 28285,
        "Negara": "Indonesia",
        "Latitude": 0.495375,
        "Longititude": 101.491202,
        "Nama Toko": "Alfarmart"
    },
    {
        "No.": 59,
        "Kecamatan": "Bukit Raya",
        "Kota": "Pekanbaru",
        "Provinsi": "Riau",
        "Kode Pos": 28131,
        "Negara": "Indonesia",
        "Latitude": 0.500282,
        "Longititude": 101.476812,
        "Nama Toko": "Indomaret"
    },
    {
        "No.": 60,
        "Kecamatan": "Bukit Raya",
        "Kota": "Pekanbaru",
        "Provinsi": "Riau",
        "Kode Pos": 28126,
        "Negara": "Indonesia",
        "Latitude": 0.500112,
        "Longititude": 101.467683,
        "Nama Toko": "Alfarmart"
    },
    {
        "No.": 61,
        "Kecamatan": "Bukit Raya",
        "Kota": "Pekanbaru",
        "Provinsi": "Riau",
        "Kode Pos": 28126,
        "Negara": "Indonesia",
        "Latitude": 0.50007,
        "Longititude": 101.467563,
        "Nama Toko": "Indomaret"
    },
    {
        "No.": 62,
        "Kecamatan": "Bukit Raya",
        "Kota": "Pekanbaru",
        "Provinsi": "Riau",
        "Kode Pos": 28126,
        "Negara": "Indonesia",
        "Latitude": 0.500502,
        "Longititude": 101.470647,
        "Nama Toko": "Indomaret"
    },
    {
        "No.": 63,
        "Kecamatan": "Bukit Raya",
        "Kota": "Pekanbaru",
        "Provinsi": "Riau",
        "Kode Pos": 28126,
        "Negara": "Indonesia",
        "Latitude": 0.500232,
        "Longititude": 101.468613,
        "Nama Toko": "Alfarmart"
    },
    {
        "No.": 64,
        "Kecamatan": "Payung Sekaki",
        "Kota": "Pekanbaru",
        "Provinsi": "Riau",
        "Kode Pos": 28292,
        "Negara": "Indonesia",
        "Latitude": 0.535225,
        "Longititude": 101.424097,
        "Nama Toko": "Indomaret"
    },
    {
        "No.": 65,
        "Kecamatan": "Bukit Raya",
        "Kota": "Pekanbaru",
        "Provinsi": "Riau",
        "Kode Pos": 28284,
        "Negara": "Indonesia",
        "Latitude": 0.50079,
        "Longititude": 101.475593,
        "Nama Toko": "Indomaret"
    },
    {
        "No.": 66,
        "Kecamatan": "Bukit Raya",
        "Kota": "Pekanbaru",
        "Provinsi": "Riau",
        "Kode Pos": 28126,
        "Negara": "Indonesia",
        "Latitude": 0.500225,
        "Longititude": 101.468587,
        "Nama Toko": "Alfarmart"
    },
    {
        "No.": 67,
        "Kecamatan": "Bukit Raya",
        "Kota": "Pekanbaru",
        "Provinsi": "Riau",
        "Kode Pos": 28126,
        "Negara": "Indonesia",
        "Latitude": 0.500215,
        "Longititude": 101.46853,
        "Nama Toko": "Alfarmart"
    },
    {
        "No.": 68,
        "Kecamatan": "Bukit Raya",
        "Kota": "Pekanbaru",
        "Provinsi": "Riau",
        "Kode Pos": 28126,
        "Negara": "Indonesia",
        "Latitude": 0.499423,
        "Longititude": 101.464597,
        "Nama Toko": "Indomaret"
    },
    {
        "No.": 69,
        "Kecamatan": "Bukit Raya",
        "Kota": "Pekanbaru",
        "Provinsi": "Riau",
        "Kode Pos": 28284,
        "Negara": "Indonesia",
        "Latitude": 0.50002,
        "Longititude": 101.46747,
        "Nama Toko": "Indomaret"
    },
    {
        "No.": 70,
        "Kecamatan": "Tenayan Raya",
        "Kota": "Pekanbaru",
        "Provinsi": "Riau",
        "Kode Pos": 28151,
        "Negara": "Indonesia",
        "Latitude": 0.531944,
        "Longititude": 101.474351,
        "Nama Toko": "Indomaret"
    },
    {
        "No.": 71,
        "Kecamatan": "Bukit Raya",
        "Kota": "Pekanbaru",
        "Provinsi": "Riau",
        "Kode Pos": 28126,
        "Negara": "Indonesia",
        "Latitude": 0.502608,
        "Longititude": 101.462252,
        "Nama Toko": "Indomaret"
    },
    {
        "No.": 72,
        "Kecamatan": "Bukit Raya",
        "Kota": "Pekanbaru",
        "Provinsi": "Riau",
        "Kode Pos": 28126,
        "Negara": "Indonesia",
        "Latitude": 0.50264,
        "Longititude": 101.462248,
        "Nama Toko": "Indomaret"
    },
    {
        "No.": 73,
        "Kecamatan": "Bukit Raya",
        "Kota": "Pekanbaru",
        "Provinsi": "Riau",
        "Kode Pos": 28289,
        "Negara": "Indonesia",
        "Latitude": 0.502878,
        "Longititude": 101.462228,
        "Nama Toko": "Indomaret"
    },
    {
        "No.": 74,
        "Kecamatan": "Bukit Raya",
        "Kota": "Pekanbaru",
        "Provinsi": "Riau",
        "Kode Pos": 28126,
        "Negara": "Indonesia",
        "Latitude": 0.499425,
        "Longititude": 101.46451,
        "Nama Toko": "Indomaret"
    },
    {
        "No.": 75,
        "Kecamatan": "Bukit Raya",
        "Kota": "Pekanbaru",
        "Provinsi": "Riau",
        "Kode Pos": 28131,
        "Negara": "Indonesia",
        "Latitude": 0.508563,
        "Longititude": 101.461658,
        "Nama Toko": "Indomaret"
    },
    {
        "No.": 76,
        "Kecamatan": "Bukit Raya",
        "Kota": "Pekanbaru",
        "Provinsi": "Riau",
        "Kode Pos": 28126,
        "Negara": "Indonesia",
        "Latitude": 0.50547,
        "Longititude": 101.462025,
        "Nama Toko": "Indomaret"
    },
    {
        "No.": 77,
        "Kecamatan": "Sail",
        "Kota": "Pekanbaru",
        "Provinsi": "Riau",
        "Kode Pos": 28127,
        "Negara": "Indonesia",
        "Latitude": 0.508738,
        "Longititude": 101.461572,
        "Nama Toko": "Indomaret"
    },
    {
        "No.": 78,
        "Kecamatan": "Sail",
        "Kota": "Pekanbaru",
        "Provinsi": "Riau",
        "Kode Pos": 28127,
        "Negara": "Indonesia",
        "Latitude": 0.513188,
        "Longititude": 101.460457,
        "Nama Toko": "Indomaret"
    },
    {
        "No.": 79,
        "Kecamatan": "Pekanbaru Kota",
        "Kota": "Pekanbaru",
        "Provinsi": "Riau",
        "Kode Pos": 28121,
        "Negara": "Indonesia",
        "Latitude": 0.512202,
        "Longititude": 101.450043,
        "Nama Toko": "Indomaret"
    }
]